hcc_topbar_buttons/__init__.py
hcc_topbar_buttons/_version.py
hcc_topbar_buttons/labextension/package.json
hcc_topbar_buttons/labextension/schemas/jupyterlab-logout/package.json.orig
hcc_topbar_buttons/labextension/schemas/jupyterlab-logout/plugin.json
hcc_topbar_buttons/labextension/static/756.95342773f3eb61f9bcce.js
hcc_topbar_buttons/labextension/static/remoteEntry.0cdb70873280aec11931.js
hcc_topbar_buttons/labextension/static/style.js
hcc_topbar_buttons/labextension/static/third-party-licenses.json
hcc_topbar_buttons-1.0.1.data/data/share/jupyter/labextensions/jupyterlab-logout/package.json
hcc_topbar_buttons-1.0.1.data/data/share/jupyter/labextensions/jupyterlab-logout/schemas/jupyterlab-logout/package.json.orig
hcc_topbar_buttons-1.0.1.data/data/share/jupyter/labextensions/jupyterlab-logout/schemas/jupyterlab-logout/plugin.json
hcc_topbar_buttons-1.0.1.data/data/share/jupyter/labextensions/jupyterlab-logout/static/756.95342773f3eb61f9bcce.js
hcc_topbar_buttons-1.0.1.data/data/share/jupyter/labextensions/jupyterlab-logout/static/remoteEntry.0cdb70873280aec11931.js
hcc_topbar_buttons-1.0.1.data/data/share/jupyter/labextensions/jupyterlab-logout/static/style.js
hcc_topbar_buttons-1.0.1.data/data/share/jupyter/labextensions/jupyterlab-logout/static/third-party-licenses.json
hcc_topbar_buttons-1.0.1.data/data/share/jupyter/labextensions/jupyterlab-logout/install.json
hcc_topbar_buttons-1.0.1.dist-info/METADATA
hcc_topbar_buttons-1.0.1.dist-info/WHEEL
hcc_topbar_buttons-1.0.1.dist-info/licenses/LICENSE
hcc_topbar_buttons-1.0.1.dist-info/RECORD
